[
    {
        "title": "The Future of AI",
        "description": "Exploring the advancements in artificial intelligence and its implications.",
        "author": "Jane Doe",
        "link": "https://example.com/article1",
        "image": "images/articles/defaultImage.png"
    },
    {
        "title": "Understanding Quantum Computing",
        "description": "An introduction to quantum computing and its potential impact on technology.",
        "author": "John Smith",
        "link": "https://example.com/article2",
        "image": "images/articles/defaultImage.png"
    },
    {
        "title": "The Rise of Electric Vehicles",
        "description": "The shift towards electric vehicles and the future of sustainable transportation.",
        "author": "Alice Johnson",
        "link": "https://example.com/article3",
        "image": "images/articles/defaultImage.png"
    },
    {
        "title": "Blockchain and Cryptocurrency",
        "description": "A deep dive into the world of blockchain technology and cryptocurrency.",
        "author": "Bob Brown",
        "link": "https://example.com/article4",
        "image": "images/articles/defaultImage.png"
    },
    {
        "title": "Cybersecurity in the Digital Age",
        "description": "How cybersecurity is evolving to protect against modern digital threats.",
        "author": "Charlie White",
        "link": "https://example.com/article5",
        "image": "images/articles/defaultImage.png"
    },
    {
        "title": "The Impact of 5G Networks",
        "description": "How 5G networks will revolutionize communication and technology.",
        "author": "Diana Green",
        "link": "https://example.com/article6",
        "image": "images/articles/defaultImage.png"
    },
    {
        "title": "Space Exploration: Past, Present, Future",
        "description": "A look at humanity's journey into space and what's to come in the future.",
        "author": "Ethan Black",
        "link": "https://example.com/article7",
        "image": "images/articles/defaultImage.png"
    },
    {
        "title": "The Psychology of Human Behavior",
        "description": "Understanding the psychological factors that influence human actions.",
        "author": "Fiona Blue",
        "link": "https://example.com/article8",
        "image": "images/articles/defaultImage.png"
    },
    {
        "title": "The Evolution of Social Media",
        "description": "How social media platforms have evolved and their influence on society.",
        "author": "George Red",
        "link": "https://example.com/article9",
        "image": "images/articles/defaultImage.png"
    },
    {
        "title": "Sustainable Energy Solutions",
        "description": "Exploring the various renewable energy sources and their potential.",
        "author": "Hannah Yellow",
        "link": "https://example.com/article10",
        "image": "images/articles/defaultImage.png"
    },
    {
        "title": "The Future of Remote Work",
        "description": "How remote work is shaping the future of the workplace.",
        "author": "Ivy Purple",
        "link": "https://example.com/article11",
        "image": "images/articles/defaultImage.png"
    },
    {
        "title": "Climate Change and Global Warming",
        "description": "The science behind climate change and what can be done to mitigate its effects.",
        "author": "Jack Gold",
        "link": "https://example.com/article12",
        "image": "images/articles/defaultImage.png"
    },
    {
        "title": "The Impact of Automation on Jobs",
        "description": "Analyzing how automation is changing the job market.",
        "author": "Kara Silver",
        "link": "https://example.com/article13",
        "image": "images/articles/defaultImage.png"
    },
    {
        "title": "Artificial Intelligence and Ethics",
        "description": "Discussing the ethical considerations surrounding AI technologies.",
        "author": "Liam Pink",
        "link": "https://example.com/article14",
        "image": "images/articles/defaultImage.png"
    },
    {
        "title": "The Role of Genetics in Medicine",
        "description": "How genetics is shaping the future of medical treatments and diagnostics.",
        "author": "Mona Brown",
        "link": "https://example.com/article15",
        "image": "images/articles/defaultImage.png"
    },
    {
        "title": "The Importance of Mental Health Awareness",
        "description": "Raising awareness about mental health issues and their impact on society.",
        "author": "Nina Blue",
        "link": "https://example.com/article16",
        "image": "images/articles/defaultImage.png"
    },
    {
        "title": "The Evolution of Mobile Technology",
        "description": "Tracking the growth and transformation of mobile technology over the years.",
        "author": "Oscar Green",
        "link": "https://example.com/article17",
        "image": "images/articles/defaultImage.png"
    },
    {
        "title": "The Importance of Cyber Hygiene",
        "description": "Best practices for maintaining cybersecurity and personal privacy online.",
        "author": "Paul Black",
        "link": "https://example.com/article18",
        "image": "images/articles/defaultImage.png"
    },
    {
        "title": "The Future of Education: Online Learning",
        "description": "How online learning platforms are transforming education.",
        "author": "Quincy Red",
        "link": "https://example.com/article19",
        "image": "images/articles/defaultImage.png"
    },
    {
        "title": "The Role of Big Data in Decision Making",
        "description": "How big data is used in business and government decision-making processes.",
        "author": "Rachel Yellow",
        "link": "https://example.com/article20",
        "image": "images/articles/defaultImage.png"
    },
    {
        "title": "The Advancements in Healthcare Technology",
        "description": "Exploring the cutting-edge technologies improving healthcare delivery.",
        "author": "Steve White",
        "link": "https://example.com/article21",
        "image": "images/articles/defaultImage.png"
    },
    {
        "title": "Nanotechnology: The Next Frontier",
        "description": "A comprehensive overview of nanotechnology and its potential applications.",
        "author": "Tina Green",
        "link": "https://example.com/article22",
        "image": "images/articles/defaultImage.png"
    },
    {
        "title": "Genomic Data and Its Potential",
        "description": "How genomic data is revolutionizing medicine and science.",
        "author": "Ursula Black",
        "link": "https://example.com/article23",
        "image": "images/articles/defaultImage.png"
    },
    {
        "title": "The Intersection of Technology and Art",
        "description": "How technology is influencing the world of art and creativity.",
        "author": "Victor Pink",
        "link": "https://example.com/article24",
        "image": "images/articles/defaultImage.png"
    },
    {
        "title": "The Growth of Smart Cities",
        "description": "The rise of smart cities and how technology is reshaping urban living.",
        "author": "Wendy Red",
        "link": "https://example.com/article25",
        "image": "images/articles/defaultImage.png"
    },
    {
        "title": "Advancements in Renewable Energy",
        "description": "The latest developments in renewable energy and sustainable power generation.",
        "author": "Xander Blue",
        "link": "https://example.com/article26",
        "image": "images/articles/defaultImage.png"
    },
    {
        "title": "The Science of Sleep",
        "description": "Understanding the science of sleep and its impact on health.",
        "author": "Yara Yellow",
        "link": "https://example.com/article27",
        "image": "images/articles/defaultImage.png"
    },
    {
        "title": "The Importance of Data Privacy",
        "description": "Protecting personal data and understanding privacy risks in the digital age.",
        "author": "Zack Green",
        "link": "https://example.com/article28",
        "image": "images/articles/defaultImage.png"
    },
    {
        "title": "The Development of Virtual Reality",
        "description": "How virtual reality is being used in entertainment, education, and medicine.",
        "author": "Aaron White",
        "link": "https://example.com/article29",
        "image": "images/articles/defaultImage.png"
    },
    {
        "title": "The Future of 3D Printing",
        "description": "Exploring the innovations in 3D printing and its potential for manufacturing.",
        "author": "Bella Pink",
        "link": "https://example.com/article30",
        "image": "images/articles/defaultImage.png"
    },
    {
        "title": "Understanding the Internet of Things",
        "description": "An introduction to IoT and its applications in daily life.",
        "author": "Chris Black",
        "link": "https://example.com/article31",
        "image": "images/articles/defaultImage.png"
    }
]
